README.md
setup.py
tuninggame/__init__.py
tuninggame/client.py
tuninggame/models.py
tuninggame.egg-info/PKG-INFO
tuninggame.egg-info/SOURCES.txt
tuninggame.egg-info/dependency_links.txt
tuninggame.egg-info/entry_points.txt
tuninggame.egg-info/top_level.txt