Metadata-Version: 1.0
Name: tuninggame
Version: 0.1.0
Summary: The sdk for the tuning game in https://github.com/tobegit3hub/tuning_game.
Home-page: https://github.com/tobegit3hub/tuning_game
Author: tobe
Author-email: tobeg3oogle@gmail.com
License: UNKNOWN
Platform: UNKNOWN
